webvtt_to_json/__init__.py
webvtt_to_json/__main__.py
webvtt_to_json/cli.py
webvtt_to_json-0.2.dist-info/LICENSE
webvtt_to_json-0.2.dist-info/METADATA
webvtt_to_json-0.2.dist-info/WHEEL
webvtt_to_json-0.2.dist-info/entry_points.txt
webvtt_to_json-0.2.dist-info/top_level.txt
webvtt_to_json-0.2.dist-info/RECORD
