Metadata-Version: 2.1
Name: webvtt-to-json
Version: 0.2
Summary: Convert WebVTT to JSON, optionally removing duplicate lines
Home-page: https://github.com/simonw/webvtt-to-json
Author: Simon Willison
License: Apache License, Version 2.0
Project-URL: Issues, https://github.com/simonw/webvtt-to-json/issues
Project-URL: CI, https://github.com/simonw/webvtt-to-json/actions
Project-URL: Changelog, https://github.com/simonw/webvtt-to-json/releases
Requires-Python: >=3.7
Provides-Extra: test
License-File: LICENSE
